adder.v
// Adder circuit

`define AND and #50
`define OR or #50
`define NOT not #50
`define NAND nand #50
`define NOR nor #50
`define XOR xor #50


module behavioralFullAdder
(
    output sum, 
    output carryout,
    input a, 
    input b, 
    input carryin
);
    // Uses concatenation operator and built-in '+'
    assign {carryout, sum}=a+b+carryin;
endmodule

module structuralFullAdder
(
    output sum, 
    output carryout,
    input a, 
    input b, 
    input carryin
);
    // Your adder code here
not notcarryin(ncarryin, carryin);
not nota(na, a);
not notb(nb, b);

and gets1(s1, na, nb, carryin);
and gets2(s2, na, b, ncarryin);
and gets3(s3, a, nb, ncarryin);
and gets4(s4, a, b, carryin);

or getsum(sum, s1, s2, s3, s4);

and getcarryout1(cout1, na, b, carryin);
and getcarryout2(cout2, a, nb, carryin);
and getcarryout3(cout3, a, b, ncarryin);
and getcarryout4(cout4, a, b, carryin);

or getcarryout(carryout, cout1, cout2, cout3, cout4);

endmodule

adder.t.v
// Adder testbench
`timescale 1 ns / 1 ps
`include "adder.v"

module testFullAdder();
    reg a, b, carryin;
    wire sum, carryout;

    structuralFullAdder adder1 (sum, carryout, a, b, carryin);
    //behavioralFullAdder adder2 (expectedsum, expectedcarryout, a, b, carryin);

    initial begin
        $dumpfile("adder.vcd");
        $dumpvars(0,adder1);

        $display("a b carryin | sum carryout");
        a=0;b=0;carryin=0; #1000
        $display("%b %b %b       | %b   %b", a, b, carryin, sum, carryout);
        a=1;b=0;carryin=0; #1000
        $display("%b %b %b       | %b   %b", a, b, carryin, sum, carryout);
        a=0;b=1;carryin=0; #1000
        $display("%b %b %b       | %b   %b", a, b, carryin, sum, carryout);
        a=1;b=1;carryin=0; #1000
        $display("%b %b %b       | %b   %b", a, b, carryin, sum, carryout);

        a=0;b=0;carryin=1; #1000
        $display("%b %b %b       | %b   %b", a, b, carryin, sum, carryout);
        a=1;b=0;carryin=1; #1000
        $display("%b %b %b       | %b   %b", a, b, carryin, sum, carryout);
        a=0;b=1;carryin=1; #1000
        $display("%b %b %b       | %b   %b", a, b, carryin, sum, carryout);
        a=1;b=1;carryin=1; #1000
        $display("%b %b %b       | %b   %b", a, b, carryin, sum, carryout);

    end
endmodule

adder.vcd
$date
	Mon Sep 25 17:23:13 2017
$end
$version
	Icarus Verilog
$end
$timescale
	1ps
$end
$scope module testFullAdder $end
$scope module adder1 $end
$var wire 1 ! a $end
$var wire 1 " b $end
$var wire 1 # carryin $end
$var wire 1 $ carryout $end
$var wire 1 % cout1 $end
$var wire 1 & cout2 $end
$var wire 1 ' cout3 $end
$var wire 1 ( cout4 $end
$var wire 1 ) na $end
$var wire 1 * nb $end
$var wire 1 + ncarryin $end
$var wire 1 , s1 $end
$var wire 1 - s2 $end
$var wire 1 . s3 $end
$var wire 1 / s4 $end
$var wire 1 0 sum $end
$upscope $end
$upscope $end
$enddefinitions $end
#0
$dumpvars
00
0/
0.
0-
0,
1+
1*
1)
0(
0'
0&
0%
0$
0#
0"
0!
$end
#1000000
10
0)
1.
1!
#2000000
0*
1-
1)
0.
1"
0!
#3000000
00
0-
1$
0)
1'
1!
#4000000
10
0$
0+
1,
1*
1)
0'
1#
0"
0!
#5000000
00
0,
1$
0)
1&
1!
#6000000
0*
1%
1)
0&
1"
0!
#7000000
0%
10
0)
1/
1(
1!
