adder.v
// Adder circuit
`define AND and #50
`define OR or #50
`define NOT not #50
`define NAND nand #50
`define NOR nor #50
`define XOR xor #50

module behavioralFullAdder
(
    output sum,
    output carryout,
    input a,
    input b,
    input carryin
);
    // Uses concatenation operator and built-in '+'
    assign {carryout, sum}=a+b+carryin;
endmodule



module structuralFullAdder
(
    output sum,
    output cout,
    input a,
    input b,
    input cin
);

    wire axb, ab, aorb, cin_aOb;
    //cin
    `AND cand0(ab, a, b);
    `OR cor0(aOb, a, b);
    `AND cand1(cin_aOb, cin, aOb);
    `OR cor1(cout, cin_aOb, ab);

    //s
    `XOR sxor0(axb, a, b);
    `XOR sxor1(sum, cin, axb);
endmodule

adder.t.v
// Adder testbench
`timescale 1 ns / 1 ps
`include "adder.v"

module testFullAdder();
    reg a, b, carryin;
    wire sum, carryout;

    //behavioralFullAdder adder (sum, carryout, a, b, carryin);
    structuralFullAdder adder (sum, carryout, a, b, carryin);

    initial begin
    $dumpfile("adder.vcd");
    $dumpvars(0, a, b, carryin, carryout, sum);
    $display(" A  B  Cin |  S Cout ");
    a = 0; b = 0; carryin = 0;
    #1000
    $display(" %b  %b    %b |  %b    %b ", a, b, carryin, sum, carryout);
    a = 1; b = 0; carryin = 0;
    #1000
    $display(" %b  %b    %b |  %b    %b ", a, b, carryin, sum, carryout);
    a = 0; b = 1; carryin = 0;
    #1000
    $display(" %b  %b    %b |  %b    %b ", a, b, carryin, sum, carryout);
    a = 1; b = 1; carryin = 0;
    #1000
    $display(" %b  %b    %b |  %b    %b ", a, b, carryin, sum, carryout);
    a = 0; b = 0; carryin = 1;
    #1000
    $display(" %b  %b    %b |  %b    %b ", a, b, carryin, sum, carryout);
    a = 1; b = 0; carryin = 1;
    #1000
    $display(" %b  %b    %b |  %b    %b ", a, b, carryin, sum, carryout);
    a = 0; b = 1; carryin = 1;
    #1000
    $display(" %b  %b    %b |  %b    %b ", a, b, carryin, sum, carryout);
    a = 1; b = 1; carryin = 1;
    #1000
    $display(" %b  %b    %b |  %b    %b ", a, b, carryin, sum, carryout);
    end
endmodule

adder.vcd
$date
	Thu Sep 21 23:09:26 2017
$end
$version
	Icarus Verilog
$end
$timescale
	1ps
$end
$scope module testFullAdder $end
$var reg 1 ! a $end
$upscope $end
$scope module testFullAdder $end
$var reg 1 " b $end
$upscope $end
$scope module testFullAdder $end
$var reg 1 # carryin $end
$upscope $end
$scope module testFullAdder $end
$var wire 1 $ carryout $end
$upscope $end
$scope module testFullAdder $end
$var wire 1 % sum $end
$upscope $end
$enddefinitions $end
#0
$dumpvars
x%
x$
0#
0"
0!
$end
#100000
0%
0$
#1000000
1!
#1100000
1%
#2000000
1"
0!
#3000000
1!
#3100000
1$
0%
#4000000
1#
0"
0!
#4050000
1%
#4150000
0$
#5000000
1!
#5100000
0%
#5150000
1$
#6000000
1"
0!
#7000000
1!
#7100000
1%
