adder.v
// Adder circuit

module behavioralFullAdder
(
    output sum,
    output carryout,
    input a,
    input b,
    input carryin
);
    // Uses concatenation operator and built-in '+'
    assign {carryout, sum}=a+b+carryin;
endmodule

module myHalfAdder(
    output sum,
    output carryout,
    input a,
    input b
);
    `XOR axorb(sum,a,b);
    `AND aandb(carryout,a,b);
endmodule

module structuralFullAdder
(
    output sum,
    output carryout,
    input a,
    input b,
    input carryin
);
    wire s1;
    wire c1;
    wire c2;
    myHalfAdder a1(s1,c1,a,b);
    myHalfAdder a2(sum, c2, s1, carryin);
    `OR (carryout, c1, c2);
endmodule

adder.t.v
// define gates with delays
`define AND and #50
`define OR or #50
`define XOR xor #50

// Adder testbench
`timescale 1 ns / 1 ps
`include "adder.v"

module testFullAdder();
    reg a, b, carryin;
    wire sum, carryout;

    structuralFullAdder dut(sum, carryout, a, b, carryin);

    initial begin
    $dumpfile("adder.vcd");
    $dumpvars(0, testFullAdder);
    $display("a | b | carryin | carryout | carryout expected | sum | sum expected | ");
    a=0;b=0;carryin=0;#200
    $display("%b | %b | %b       | %b        | %s                 | %b   | %s            | ", a, b, carryin, carryout, "0", sum, "0");
    a=0;b=0;carryin=1;#200
    $display("%b | %b | %b       | %b        | %s                 | %b   | %s            | ", a, b, carryin, carryout, "0", sum, "1");
    a=0;b=1;carryin=0;#200
    $display("%b | %b | %b       | %b        | %s                 | %b   | %s            | ", a, b, carryin, carryout, "0", sum, "1");
    a=0;b=1;carryin=1;#200
    $display("%b | %b | %b       | %b        | %s                 | %b   | %s            | ", a, b, carryin, carryout, "1", sum, "0");
    a=1;b=0;carryin=0;#200
    $display("%b | %b | %b       | %b        | %s                 | %b   | %s            | ", a, b, carryin, carryout, "0", sum, "1");
    a=1;b=0;carryin=1;#200
    $display("%b | %b | %b       | %b        | %s                 | %b   | %s            | ", a, b, carryin, carryout, "1", sum, "0");
    a=1;b=1;carryin=0;#200
    $display("%b | %b | %b       | %b        | %s                 | %b   | %s            | ", a, b, carryin, carryout, "1", sum, "0");
    a=1;b=1;carryin=1;#200
    $display("%b | %b | %b       | %b        | %s                 | %b   | %s            | ", a, b, carryin, carryout, "1", sum, "1");
    end
endmodule

adder.vcd
$date
	Thu Sep 21 20:51:58 2017
$end
$version
	Icarus Verilog
$end
$timescale
	1ps
$end
$scope module testFullAdder $end
$var wire 1 ! sum $end
$var wire 1 " carryout $end
$var reg 1 # a $end
$var reg 1 $ b $end
$var reg 1 % carryin $end
$scope module dut $end
$var wire 1 # a $end
$var wire 1 $ b $end
$var wire 1 % carryin $end
$var wire 1 " carryout $end
$var wire 1 ! sum $end
$var wire 1 & s1 $end
$var wire 1 ' c2 $end
$var wire 1 ( c1 $end
$scope module a1 $end
$var wire 1 # a $end
$var wire 1 $ b $end
$var wire 1 ( carryout $end
$var wire 1 & sum $end
$upscope $end
$scope module a2 $end
$var wire 1 & a $end
$var wire 1 % b $end
$var wire 1 ' carryout $end
$var wire 1 ! sum $end
$upscope $end
$upscope $end
$upscope $end
$enddefinitions $end
#0
$dumpvars
x(
x'
x&
0%
0$
0#
x"
x!
$end
#50000
0'
0(
0&
#100000
0"
0!
#200000
1%
#250000
1!
#400000
0%
1$
#450000
0!
1&
#500000
1!
#600000
1%
#650000
0!
1'
#700000
1"
#800000
0%
0$
1#
#850000
1!
0'
#900000
0"
#1000000
1%
#1050000
0!
1'
#1100000
1"
#1200000
0%
1$
#1250000
1!
0'
0&
1(
#1300000
0!
#1400000
1%
#1450000
1!
