decoder.v
// Decoder circuit

module behavioralDecoder
(
    output out0, out1, out2, out3,
    input address0, address1,
    input enable
);
    // Uses concatenation and shift operators
    assign {out3,out2,out1,out0}=enable<<{address1,address0};
endmodule


module oneBitDecoder(
  output out0, out1,
  input address,
  input enable
);
wire _address;
`NOT nAd(_address, address);
`AND o0(out0, _address, enable);
`AND o1(out1,  address, enable);
endmodule //#100

module structuralDecoder
(
    output out0, out1, out2, out3,
    input address0, address1,
    input enable
);
    wire w0,w1;
    oneBitDecoder d1(w0,w1,address1,enable); //#100
    oneBitDecoder d2(out0, out1, address0, w0); //#200
    oneBitDecoder d3(out2, out3, address0, w1); //#200
endmodule

decoder.t.v
// Decoder testbench
`timescale 1 ns / 1 ps
`include "decoder.v"

module testDecoder ();
    reg addr0, addr1;
    reg enable;
    wire out0,out1,out2,out3;

    //behavioralDecoder decoder (out0,out1,out2,out3,addr0,addr1,enable);
    structuralDecoder decoder (out0,out1,out2,out3,addr0,addr1,enable); // Swap after testing

    initial begin
    $dumpfile("decoder.vcd");
    $dumpvars(0, addr0, addr1, enable, out0, out1, out2, out3);
    $display("En A0 A1| O0 O1 O2 O3 | Expected Output");
    enable=0;addr0=0;addr1=0; #1000
    $display("%b  %b  %b |  %b  %b  %b  %b | All false", enable, addr0, addr1, out0, out1, out2, out3);
    enable=0;addr0=1;addr1=0; #1000
    $display("%b  %b  %b |  %b  %b  %b  %b | All false", enable, addr0, addr1, out0, out1, out2, out3);
    enable=0;addr0=0;addr1=1; #1000
    $display("%b  %b  %b |  %b  %b  %b  %b | All false", enable, addr0, addr1, out0, out1, out2, out3);
    enable=0;addr0=1;addr1=1; #1000
    $display("%b  %b  %b |  %b  %b  %b  %b | All false", enable, addr0, addr1, out0, out1, out2, out3);
    enable=1;addr0=0;addr1=0; #1000
    $display("%b  %b  %b |  %b  %b  %b  %b | O0 Only", enable, addr0, addr1, out0, out1, out2, out3);
    enable=1;addr0=1;addr1=0; #1000
    $display("%b  %b  %b |  %b  %b  %b  %b | O1 Only", enable, addr0, addr1, out0, out1, out2, out3);
    enable=1;addr0=0;addr1=1; #1000
    $display("%b  %b  %b |  %b  %b  %b  %b | O2 Only", enable, addr0, addr1, out0, out1, out2, out3);
    enable=1;addr0=1;addr1=1; #1000
    $display("%b  %b  %b |  %b  %b  %b  %b | O3 Only", enable, addr0, addr1, out0, out1, out2, out3);
    end

endmodule

decoder.vcd
$date
	Thu Sep 21 21:07:41 2017
$end
$version
	Icarus Verilog
$end
$timescale
	1ps
$end
$scope module testDecoder $end
$var wire 1 ! out3 $end
$var wire 1 " out2 $end
$var wire 1 # out1 $end
$var wire 1 $ out0 $end
$var reg 1 % addr0 $end
$var reg 1 & addr1 $end
$var reg 1 ' enable $end
$scope module decoder $end
$var wire 1 % address0 $end
$var wire 1 & address1 $end
$var wire 1 ' enable $end
$var wire 1 ( w1 $end
$var wire 1 ) w0 $end
$var wire 1 ! out3 $end
$var wire 1 " out2 $end
$var wire 1 # out1 $end
$var wire 1 $ out0 $end
$scope module d1 $end
$var wire 1 * _address $end
$var wire 1 & address $end
$var wire 1 ' enable $end
$var wire 1 ) out0 $end
$var wire 1 ( out1 $end
$upscope $end
$scope module d2 $end
$var wire 1 + _address $end
$var wire 1 % address $end
$var wire 1 ) enable $end
$var wire 1 $ out0 $end
$var wire 1 # out1 $end
$upscope $end
$scope module d3 $end
$var wire 1 , _address $end
$var wire 1 % address $end
$var wire 1 ( enable $end
$var wire 1 " out0 $end
$var wire 1 ! out1 $end
$upscope $end
$upscope $end
$upscope $end
$enddefinitions $end
#0
$dumpvars
x,
x+
x*
x)
x(
0'
0&
0%
x$
x#
x"
x!
$end
#50000
1*
1+
1,
0!
0#
0(
0)
#100000
0"
0$
#1000000
1%
#1050000
0+
0,
#2000000
1&
0%
#2050000
0*
1+
1,
#3000000
1%
#3050000
0+
0,
#4000000
0&
0%
1'
#4050000
1*
1+
1,
#4100000
1)
#4150000
1$
#5000000
1%
#5050000
0+
1#
0,
#5100000
0$
#6000000
1&
0%
#6050000
0*
1(
1+
0#
1,
#6100000
0)
1$
1"
#6150000
0$
#7000000
1%
#7050000
0+
0,
1!
#7100000
0"
