decoder.v
// Decoder circuit
`define AND and #50
`define OR or #50
`define NOT not #50
`define NAND nand #50
`define NOR nor #50
`define XOR xor #50


module behavioralDecoder
(
    output out0, out1, out2, out3,
    input address0, address1,
    input enable
);
    // Uses concatenation and shift operators
    assign {out3,out2,out1,out0}=enable<<{address1,address0};
endmodule


module structuralDecoder
(
    output out0, out1, out2, out3,
    input A0, A1,
    input Enable
);

// Your decoder code here
not A0inv(nA0, A0);
not A1inv(nA1, A1);
and andnA0nA1(nA0andnA1, nA0, nA1);   // and nA0 and nA1
and andA0andnA1(A0andnA1, A0, nA1);   // and A0 and nA1
and andnA0andA1(nA0andA1, nA0, A1);   // and nA0 and A1
and andA0andA1(A0andA1, A0, A1);      // and A0 and A1

and getout0(out0, Enable, nA0andnA1); // out0 obtained from nA0andnA1
and getout1(out1, Enable, A0andnA1);  // out1 obtained from A0andnA1
and getout2(out2, Enable, nA0andA1);  // out2 obtained from nA0andA1
and getout3(out3, Enable, A0andA1);   // out3 obtained from A0andA1

endmodule

decoder.t.v
// Decoder testbench
`timescale 1 ns / 1 ps
`include "decoder.v"

module testDecoder ();
    reg addr0, addr1;
    reg enable;
    wire out0,out1,out2,out3;

    //behavioralDecoder decoder (out0,out1,out2,out3,addr0,addr1,enable);
    structuralDecoder decoder (out0,out1,out2,out3,addr0,addr1,enable); // Swap after testing

    initial begin
    $dumpfile("decoder.vcd");
    $dumpvars(0, addr0, addr1, enable, out0, out1, out2, out3);
    $display("En A0 A1| O0 O1 O2 O3 | Expected Output");
    enable=0;addr0=0;addr1=0; #1000
    $display("%b  %b  %b |  %b  %b  %b  %b | All false", enable, addr0, addr1, out0, out1, out2, out3);
    enable=0;addr0=1;addr1=0; #1000
    $display("%b  %b  %b |  %b  %b  %b  %b | All false", enable, addr0, addr1, out0, out1, out2, out3);
    enable=0;addr0=0;addr1=1; #1000
    $display("%b  %b  %b |  %b  %b  %b  %b | All false", enable, addr0, addr1, out0, out1, out2, out3);
    enable=0;addr0=1;addr1=1; #1000
    $display("%b  %b  %b |  %b  %b  %b  %b | All false", enable, addr0, addr1, out0, out1, out2, out3);
    enable=1;addr0=0;addr1=0; #1000
    $display("%b  %b  %b |  %b  %b  %b  %b | O0 Only", enable, addr0, addr1, out0, out1, out2, out3);
    enable=1;addr0=1;addr1=0; #1000
    $display("%b  %b  %b |  %b  %b  %b  %b | O1 Only", enable, addr0, addr1, out0, out1, out2, out3);
    enable=1;addr0=0;addr1=1; #1000
    $display("%b  %b  %b |  %b  %b  %b  %b | O2 Only", enable, addr0, addr1, out0, out1, out2, out3);
    enable=1;addr0=1;addr1=1; #1000
    $display("%b  %b  %b |  %b  %b  %b  %b | O3 Only", enable, addr0, addr1, out0, out1, out2, out3);
    end

endmodule

decoder.vcd
$date
	Mon Sep 25 17:23:53 2017
$end
$version
	Icarus Verilog
$end
$timescale
	1ps
$end
$scope module testDecoder $end
$scope module decoder $end
$var wire 1 ! A0 $end
$var wire 1 " A0andA1 $end
$var wire 1 # A0andnA1 $end
$var wire 1 $ A1 $end
$var wire 1 % Enable $end
$var wire 1 & nA0 $end
$var wire 1 ' nA0andA1 $end
$var wire 1 ( nA0andnA1 $end
$var wire 1 ) nA1 $end
$var wire 1 * out0 $end
$var wire 1 + out1 $end
$var wire 1 , out2 $end
$var wire 1 - out3 $end
$upscope $end
$upscope $end
$enddefinitions $end
#0
$dumpvars
0-
0,
0+
0*
1)
1(
0'
1&
0%
0$
0#
0"
0!
$end
#1000000
0(
0&
1#
1!
#2000000
0)
1'
1&
0#
1$
0!
#3000000
0'
0&
1"
1!
#4000000
1*
1(
1)
1&
0"
0-
0$
0!
1%
#5000000
0*
0(
1+
0&
1#
1!
#6000000
1,
0+
0)
1'
1&
0#
1$
0!
#7000000
0,
0'
1-
0&
1"
1!
