decoder.v
// Decoder circuit
`define AND and #50
`define OR or #50
`define NOT not #50
`define XOR xor #50

module behavioralDecoder
(
    output out0, out1, out2, out3,
    input address0, address1,
    input enable
);
    // Uses concatenation and shift operators
    assign {out3,out2,out1,out0}=enable<<{address1,address0};
endmodule


module structuralDecoder
(
    output Sout0, Sout1, Sout2, Sout3,
    input address0, address1,
    input enable
);
    // Your decoder code here
	wire naddress0;
	wire naddress1;
	wire nA0nA1;
	wire A0nA1;
	wire nA0A1;
	wire A0A1;

	`NOT A0inv(naddress0, address0);
	`NOT A1inv(naddress1, address1);
	`AND andgate1(nA0nA1, naddress0, naddress1);
	`AND andgate2(Sout0, enable, nA0nA1);

	`AND andgate3(A0nA1, address0, naddress1);
	`AND andgate4(Sout1, enable, A0nA1);

	`AND andgate5(nA0A1, naddress0, address1);
	`AND andgate6(Sout2, enable, nA0A1);

	`AND andgate7(A0A1, address0, address1);
	`AND andgate8(Sout3, enable, A0A1);

endmodule

decoder.t.v
// Decoder testbench
`timescale 1 ns / 1 ps
`include "decoder.v"

module testDecoder (); 
    wire out0,out1,out2,out3;
	wire Sout0, Sout1, Sout2, Sout3;
    reg addr0, addr1;
    reg enable;


    behavioralDecoder decoder (out0,out1,out2,out3,addr0,addr1,enable);
    structuralDecoder structuraltest(Sout0,Sout1,Sout2,Sout3,addr0,addr1,enable); 

    initial begin

	$dumpfile("decoder.vcd");
	$dumpvars();

	$display("Behavioral Decoder");
    $display("En A0 A1| O0 O1 O2 O3 | Expected Output");
    enable=0;addr0=0;addr1=0; #1000 
    $display("%b  %b  %b |  %b  %b  %b  %b | All false", enable, addr0, addr1, out0, out1, out2, out3);
    enable=0;addr0=1;addr1=0; #1000
    $display("%b  %b  %b |  %b  %b  %b  %b | All false", enable, addr0, addr1, out0, out1, out2, out3);
    enable=0;addr0=0;addr1=1; #1000 
    $display("%b  %b  %b |  %b  %b  %b  %b | All false", enable, addr0, addr1, out0, out1, out2, out3);
    enable=0;addr0=1;addr1=1; #1000 
    $display("%b  %b  %b |  %b  %b  %b  %b | All false", enable, addr0, addr1, out0, out1, out2, out3);
    enable=1;addr0=0;addr1=0; #1000 
    $display("%b  %b  %b |  %b  %b  %b  %b | O0 Only", enable, addr0, addr1, out0, out1, out2, out3);
    enable=1;addr0=1;addr1=0; #1000 
    $display("%b  %b  %b |  %b  %b  %b  %b | O1 Only", enable, addr0, addr1, out0, out1, out2, out3);
    enable=1;addr0=0;addr1=1; #1000 
    $display("%b  %b  %b |  %b  %b  %b  %b | O2 Only", enable, addr0, addr1, out0, out1, out2, out3);
    enable=1;addr0=1;addr1=1; #1000 
    $display("%b  %b  %b |  %b  %b  %b  %b | O3 Only", enable, addr0, addr1, out0, out1, out2, out3);

	$display("Structural Decoder");
    $display("En A0 A1| O0 O1 O2 O3 | Expected Output");
    enable=0;addr0=0;addr1=0; #1000 
    $display("%b  %b  %b |  %b  %b  %b  %b | All false", enable, addr0, addr1, Sout0, Sout1, Sout2, Sout3);
    enable=0;addr0=1;addr1=0; #1000
    $display("%b  %b  %b |  %b  %b  %b  %b | All false", enable, addr0, addr1, Sout0, Sout1, Sout2, Sout3);
    enable=0;addr0=0;addr1=1; #1000 
    $display("%b  %b  %b |  %b  %b  %b  %b | All false", enable, addr0, addr1, Sout0, Sout1, Sout2, Sout3);
    enable=0;addr0=1;addr1=1; #1000 
    $display("%b  %b  %b |  %b  %b  %b  %b | All false", enable, addr0, addr1, Sout0, Sout1, Sout2, Sout3);
    enable=1;addr0=0;addr1=0; #1000 
    $display("%b  %b  %b |  %b  %b  %b  %b | O0 Only", enable, addr0, addr1, Sout0, Sout1, Sout2, Sout3);
    enable=1;addr0=1;addr1=0; #1000 
    $display("%b  %b  %b |  %b  %b  %b  %b | O1 Only", enable, addr0, addr1, Sout0, Sout1, Sout2, Sout3);
    enable=1;addr0=0;addr1=1; #1000 
    $display("%b  %b  %b |  %b  %b  %b  %b | O2 Only", enable, addr0, addr1, Sout0, Sout1, Sout2, Sout3);
    enable=1;addr0=1;addr1=1; #1000 
    $display("%b  %b  %b |  %b  %b  %b  %b | O3 Only", enable, addr0, addr1, Sout0, Sout1, Sout2, Sout3);
    end
endmodule

decoder.vcd
$date
	Thu Sep 21 19:55:29 2017
$end
$version
	Icarus Verilog
$end
$timescale
	1ps
$end
$scope module testDecoder $end
$var wire 1 ! Sout0 $end
$var wire 1 " Sout1 $end
$var wire 1 # Sout2 $end
$var wire 1 $ Sout3 $end
$var wire 1 % out0 $end
$var wire 1 & out1 $end
$var wire 1 ' out2 $end
$var wire 1 ( out3 $end
$var reg 1 ) addr0 $end
$var reg 1 * addr1 $end
$var reg 1 + enable $end
$scope module decoder $end
$var wire 1 , address0 $end
$var wire 1 - address1 $end
$var wire 1 . enable $end
$var wire 1 % out0 $end
$var wire 1 & out1 $end
$var wire 1 ' out2 $end
$var wire 1 ( out3 $end
$upscope $end
$scope module structuraltest $end
$var wire 1 / A0A1 $end
$var wire 1 0 A0nA1 $end
$var wire 1 ! Sout0 $end
$var wire 1 " Sout1 $end
$var wire 1 # Sout2 $end
$var wire 1 $ Sout3 $end
$var wire 1 , address0 $end
$var wire 1 - address1 $end
$var wire 1 . enable $end
$var wire 1 1 nA0A1 $end
$var wire 1 2 nA0nA1 $end
$var wire 1 3 naddress0 $end
$var wire 1 4 naddress1 $end
$upscope $end
$upscope $end
$enddefinitions $end
#0
$dumpvars
z4
z3
x2
z1
z0
z/
0.
0-
0,
0+
0*
0)
0(
0'
0&
0%
z$
z#
z"
z!
$end
#50000
0$
0/
0#
01
0"
00
0!
13
14
#100000
12
#1000000
1)
1,
#1050000
03
10
#1100000
02
#2000000
1*
1-
0)
0,
#2050000
04
13
00
#2100000
11
#3000000
1)
1,
#3050000
03
1/
#3100000
01
#4000000
1%
0*
0-
0)
0,
1+
1.
#4050000
14
13
0/
1$
#4100000
12
0$
#4150000
1!
#5000000
0%
1&
1)
1,
#5050000
03
10
#5100000
02
1"
#5150000
0!
#6000000
1'
0&
1*
1-
0)
0,
#6050000
04
13
00
#6100000
11
0"
#6150000
1#
#7000000
0'
1(
1)
1,
#7050000
03
1/
#7100000
01
1$
#7150000
0#
#8000000
0(
0*
0-
0)
0,
0+
0.
#8050000
14
13
0/
0$
#8100000
12
#9000000
1)
1,
#9050000
03
10
#9100000
02
#10000000
1*
1-
0)
0,
#10050000
04
13
00
#10100000
11
#11000000
1)
1,
#11050000
03
1/
#11100000
01
#12000000
1%
0*
0-
0)
0,
1+
1.
#12050000
14
13
0/
1$
#12100000
12
0$
#12150000
1!
#13000000
0%
1&
1)
1,
#13050000
03
10
#13100000
02
1"
#13150000
0!
#14000000
1'
0&
1*
1-
0)
0,
#14050000
04
13
00
#14100000
11
0"
#14150000
1#
#15000000
0'
1(
1)
1,
#15050000
03
1/
#15100000
01
1$
#15150000
0#
