decoder.v
// Decoder circuit

`define AND and #50
`define NOT not #50

module behavioralDecoder
(
    output out0, out1, out2, out3,
    input address0, address1,
    input enable
);
    // Uses concatenation and shift operators
    assign {out3,out2,out1,out0}=enable<<{address1,address0};
endmodule


module structuralDecoder
(
    output out0, out1, out2, out3,
    input address0, address1,
    input enable
);
    
    wire nA0;
    wire nA1;
    wire nA0andnA1;
    wire A0andnA1;
    wire nA0andA1;
    wire A0andA1;

    `NOT A0inv(nA0, address0);
    `NOT A1inv(nA1, address1);

    `AND andgate00(nA0andnA1, nA0, nA1);
    `AND andgate01(A0andnA1, address0, nA1);
    `AND andgate02(nA0andA1, nA0, address1);
    `AND andgate03(A0andA1, address0, address1);

    `AND andgateout0(out0, enable, nA0andnA1);
    `AND andgateout1(out1, enable, A0andnA1);
    `AND andgateout2(out2, enable, nA0andA1);
    `AND andgateout3(out3, enable, A0andA1);

endmodule

decoder.t.v
// Decoder testbench
`timescale 1 ns / 1 ps
`include "decoder.v"

module testDecoder ();
    reg addr0, addr1;
    reg enable;
    wire out0,out1,out2,out3;

    //behavioralDecoder decoder (out0,out1,out2,out3,addr0,addr1,enable);
    structuralDecoder decoder (out0,out1,out2,out3,addr0,addr1,enable); // Swap after testing

    initial begin
    $dumpfile("decoder.vcd");
    $dumpvars(0, addr0, addr1, enable, out0, out1, out2, out3);
    $display("En A0 A1| O0 O1 O2 O3 | Expected Output");
    enable=0;addr0=0;addr1=0; #1000
    $display("%b  %b  %b |  %b  %b  %b  %b | All false", enable, addr0, addr1, out0, out1, out2, out3);
    enable=0;addr0=1;addr1=0; #1000
    $display("%b  %b  %b |  %b  %b  %b  %b | All false", enable, addr0, addr1, out0, out1, out2, out3);
    enable=0;addr0=0;addr1=1; #1000
    $display("%b  %b  %b |  %b  %b  %b  %b | All false", enable, addr0, addr1, out0, out1, out2, out3);
    enable=0;addr0=1;addr1=1; #1000
    $display("%b  %b  %b |  %b  %b  %b  %b | All false", enable, addr0, addr1, out0, out1, out2, out3);
    enable=1;addr0=0;addr1=0; #1000
    $display("%b  %b  %b |  %b  %b  %b  %b | O0 Only", enable, addr0, addr1, out0, out1, out2, out3);
    enable=1;addr0=1;addr1=0; #1000
    $display("%b  %b  %b |  %b  %b  %b  %b | O1 Only", enable, addr0, addr1, out0, out1, out2, out3);
    enable=1;addr0=0;addr1=1; #1000
    $display("%b  %b  %b |  %b  %b  %b  %b | O2 Only", enable, addr0, addr1, out0, out1, out2, out3);
    enable=1;addr0=1;addr1=1; #1000
    $display("%b  %b  %b |  %b  %b  %b  %b | O3 Only", enable, addr0, addr1, out0, out1, out2, out3);
    end

endmodule

decoder.vcd
$date
	Thu Sep 21 23:09:14 2017
$end
$version
	Icarus Verilog
$end
$timescale
	1ps
$end
$scope module testDecoder $end
$var reg 1 ! addr0 $end
$upscope $end
$scope module testDecoder $end
$var reg 1 " addr1 $end
$upscope $end
$scope module testDecoder $end
$var reg 1 # enable $end
$upscope $end
$scope module testDecoder $end
$var wire 1 $ out0 $end
$upscope $end
$scope module testDecoder $end
$var wire 1 % out1 $end
$upscope $end
$scope module testDecoder $end
$var wire 1 & out2 $end
$upscope $end
$scope module testDecoder $end
$var wire 1 ' out3 $end
$upscope $end
$enddefinitions $end
#0
$dumpvars
x'
x&
x%
x$
0#
0"
0!
$end
#50000
0'
0&
0%
0$
#1000000
1!
#2000000
1"
0!
#3000000
1!
#4000000
0"
0!
1#
#4050000
1'
#4100000
0'
#4150000
1$
#5000000
1!
#5100000
1%
#5150000
0$
#6000000
1"
0!
#6100000
0%
#6150000
1&
#7000000
1!
#7100000
1'
#7150000
0&
