multiplexer.v
// Multiplexer circuit

module behavioralMultiplexer
(
    output out,
    input address0, address1,
    input in0, in1, in2, in3
);
    // Join single-bit inputs into a bus, use address as index
    wire[3:0] inputs = {in3, in2, in1, in0};
    wire[1:0] address = {address1, address0};
    assign out = inputs[address];
endmodule

module oneBitMux(
  output out,
  input address,
  input in0, in1
);
  wire _address, w0, w1;
  `NOT nAd(_address, address);
  `AND a1(w0, in0, _address);
  `AND a2(w1, in1, address);
  `OR   o(out, w0, w1);
endmodule

module structuralMultiplexer
(
    output out,
    input address0, address1,
    input in0, in1, in2, in3
);
    wire w0, w1;
    oneBitMux m1(w0, address0, in0, in1);
    oneBitMux m2(w1, address0, in2, in3);
    oneBitMux m3(out, address1, w0, w1);
endmodule

multiplexer.t.v
// Multiplexer testbench
`define AND and #50
`define OR or #50
`define NOT not #50
`timescale 1 ns / 1 ps
`include "multiplexer.v"

module testMultiplexer ();
  reg address0, address1;
  reg in0, in1, in2, in3;
  wire out;

  structuralMultiplexer dut(out, address0, address1, in0, in1, in2, in3);
  initial begin
  $dumpfile("mux.vcd");
  $dumpvars(0, testMultiplexer);
  $display("address0 | address1 | in0 | in1 | in2 | in3 | out | out expected | ");
  address0=0;address1=0;in0=0;in1=0;in2=0;in3=0;#1000
  $display("%b        | %b        | %b   | %b   | %b   | %b   | %b   | %s            | ", address0, address1, in0, in1, in2, in3, out, "0");
  address0=0;address1=0;in0=0;in1=0;in2=0;in3=1;#1000
  $display("%b        | %b        | %b   | %b   | %b   | %b   | %b   | %s            | ", address0, address1, in0, in1, in2, in3, out, "0");
  address0=0;address1=0;in0=0;in1=0;in2=1;in3=0;#1000
  $display("%b        | %b        | %b   | %b   | %b   | %b   | %b   | %s            | ", address0, address1, in0, in1, in2, in3, out, "0");
  address0=0;address1=0;in0=0;in1=0;in2=1;in3=1;#1000
  $display("%b        | %b        | %b   | %b   | %b   | %b   | %b   | %s            | ", address0, address1, in0, in1, in2, in3, out, "0");
  address0=0;address1=0;in0=0;in1=1;in2=0;in3=0;#1000
  $display("%b        | %b        | %b   | %b   | %b   | %b   | %b   | %s            | ", address0, address1, in0, in1, in2, in3, out, "0");
  address0=0;address1=0;in0=0;in1=1;in2=0;in3=1;#1000
  $display("%b        | %b        | %b   | %b   | %b   | %b   | %b   | %s            | ", address0, address1, in0, in1, in2, in3, out, "0");
  address0=0;address1=0;in0=0;in1=1;in2=1;in3=0;#1000
  $display("%b        | %b        | %b   | %b   | %b   | %b   | %b   | %s            | ", address0, address1, in0, in1, in2, in3, out, "0");
  address0=0;address1=0;in0=0;in1=1;in2=1;in3=1;#1000
  $display("%b        | %b        | %b   | %b   | %b   | %b   | %b   | %s            | ", address0, address1, in0, in1, in2, in3, out, "0");
  address0=0;address1=0;in0=1;in1=0;in2=0;in3=0;#1000
  $display("%b        | %b        | %b   | %b   | %b   | %b   | %b   | %s            | ", address0, address1, in0, in1, in2, in3, out, "1");
  address0=0;address1=0;in0=1;in1=0;in2=0;in3=1;#1000
  $display("%b        | %b        | %b   | %b   | %b   | %b   | %b   | %s            | ", address0, address1, in0, in1, in2, in3, out, "1");
  address0=0;address1=0;in0=1;in1=0;in2=1;in3=0;#1000
  $display("%b        | %b        | %b   | %b   | %b   | %b   | %b   | %s            | ", address0, address1, in0, in1, in2, in3, out, "1");
  address0=0;address1=0;in0=1;in1=0;in2=1;in3=1;#1000
  $display("%b        | %b        | %b   | %b   | %b   | %b   | %b   | %s            | ", address0, address1, in0, in1, in2, in3, out, "1");
  address0=0;address1=0;in0=1;in1=1;in2=0;in3=0;#1000
  $display("%b        | %b        | %b   | %b   | %b   | %b   | %b   | %s            | ", address0, address1, in0, in1, in2, in3, out, "1");
  address0=0;address1=0;in0=1;in1=1;in2=0;in3=1;#1000
  $display("%b        | %b        | %b   | %b   | %b   | %b   | %b   | %s            | ", address0, address1, in0, in1, in2, in3, out, "1");
  address0=0;address1=0;in0=1;in1=1;in2=1;in3=0;#1000
  $display("%b        | %b        | %b   | %b   | %b   | %b   | %b   | %s            | ", address0, address1, in0, in1, in2, in3, out, "1");
  address0=0;address1=0;in0=1;in1=1;in2=1;in3=1;#1000
  $display("%b        | %b        | %b   | %b   | %b   | %b   | %b   | %s            | ", address0, address1, in0, in1, in2, in3, out, "1");
  address0=0;address1=1;in0=0;in1=0;in2=0;in3=0;#1000
  $display("%b        | %b        | %b   | %b   | %b   | %b   | %b   | %s            | ", address0, address1, in0, in1, in2, in3, out, "0");
  address0=0;address1=1;in0=0;in1=0;in2=0;in3=1;#1000
  $display("%b        | %b        | %b   | %b   | %b   | %b   | %b   | %s            | ", address0, address1, in0, in1, in2, in3, out, "0");
  address0=0;address1=1;in0=0;in1=0;in2=1;in3=0;#1000
  $display("%b        | %b        | %b   | %b   | %b   | %b   | %b   | %s            | ", address0, address1, in0, in1, in2, in3, out, "1");
  address0=0;address1=1;in0=0;in1=0;in2=1;in3=1;#1000
  $display("%b        | %b        | %b   | %b   | %b   | %b   | %b   | %s            | ", address0, address1, in0, in1, in2, in3, out, "1");
  address0=0;address1=1;in0=0;in1=1;in2=0;in3=0;#1000
  $display("%b        | %b        | %b   | %b   | %b   | %b   | %b   | %s            | ", address0, address1, in0, in1, in2, in3, out, "0");
  address0=0;address1=1;in0=0;in1=1;in2=0;in3=1;#1000
  $display("%b        | %b        | %b   | %b   | %b   | %b   | %b   | %s            | ", address0, address1, in0, in1, in2, in3, out, "0");
  address0=0;address1=1;in0=0;in1=1;in2=1;in3=0;#1000
  $display("%b        | %b        | %b   | %b   | %b   | %b   | %b   | %s            | ", address0, address1, in0, in1, in2, in3, out, "1");
  address0=0;address1=1;in0=0;in1=1;in2=1;in3=1;#1000
  $display("%b        | %b        | %b   | %b   | %b   | %b   | %b   | %s            | ", address0, address1, in0, in1, in2, in3, out, "1");
  address0=0;address1=1;in0=1;in1=0;in2=0;in3=0;#1000
  $display("%b        | %b        | %b   | %b   | %b   | %b   | %b   | %s            | ", address0, address1, in0, in1, in2, in3, out, "0");
  address0=0;address1=1;in0=1;in1=0;in2=0;in3=1;#1000
  $display("%b        | %b        | %b   | %b   | %b   | %b   | %b   | %s            | ", address0, address1, in0, in1, in2, in3, out, "0");
  address0=0;address1=1;in0=1;in1=0;in2=1;in3=0;#1000
  $display("%b        | %b        | %b   | %b   | %b   | %b   | %b   | %s            | ", address0, address1, in0, in1, in2, in3, out, "1");
  address0=0;address1=1;in0=1;in1=0;in2=1;in3=1;#1000
  $display("%b        | %b        | %b   | %b   | %b   | %b   | %b   | %s            | ", address0, address1, in0, in1, in2, in3, out, "1");
  address0=0;address1=1;in0=1;in1=1;in2=0;in3=0;#1000
  $display("%b        | %b        | %b   | %b   | %b   | %b   | %b   | %s            | ", address0, address1, in0, in1, in2, in3, out, "0");
  address0=0;address1=1;in0=1;in1=1;in2=0;in3=1;#1000
  $display("%b        | %b        | %b   | %b   | %b   | %b   | %b   | %s            | ", address0, address1, in0, in1, in2, in3, out, "0");
  address0=0;address1=1;in0=1;in1=1;in2=1;in3=0;#1000
  $display("%b        | %b        | %b   | %b   | %b   | %b   | %b   | %s            | ", address0, address1, in0, in1, in2, in3, out, "1");
  address0=0;address1=1;in0=1;in1=1;in2=1;in3=1;#1000
  $display("%b        | %b        | %b   | %b   | %b   | %b   | %b   | %s            | ", address0, address1, in0, in1, in2, in3, out, "1");
  address0=1;address1=0;in0=0;in1=0;in2=0;in3=0;#1000
  $display("%b        | %b        | %b   | %b   | %b   | %b   | %b   | %s            | ", address0, address1, in0, in1, in2, in3, out, "0");
  address0=1;address1=0;in0=0;in1=0;in2=0;in3=1;#1000
  $display("%b        | %b        | %b   | %b   | %b   | %b   | %b   | %s            | ", address0, address1, in0, in1, in2, in3, out, "0");
  address0=1;address1=0;in0=0;in1=0;in2=1;in3=0;#1000
  $display("%b        | %b        | %b   | %b   | %b   | %b   | %b   | %s            | ", address0, address1, in0, in1, in2, in3, out, "0");
  address0=1;address1=0;in0=0;in1=0;in2=1;in3=1;#1000
  $display("%b        | %b        | %b   | %b   | %b   | %b   | %b   | %s            | ", address0, address1, in0, in1, in2, in3, out, "0");
  address0=1;address1=0;in0=0;in1=1;in2=0;in3=0;#1000
  $display("%b        | %b        | %b   | %b   | %b   | %b   | %b   | %s            | ", address0, address1, in0, in1, in2, in3, out, "1");
  address0=1;address1=0;in0=0;in1=1;in2=0;in3=1;#1000
  $display("%b        | %b        | %b   | %b   | %b   | %b   | %b   | %s            | ", address0, address1, in0, in1, in2, in3, out, "1");
  address0=1;address1=0;in0=0;in1=1;in2=1;in3=0;#1000
  $display("%b        | %b        | %b   | %b   | %b   | %b   | %b   | %s            | ", address0, address1, in0, in1, in2, in3, out, "1");
  address0=1;address1=0;in0=0;in1=1;in2=1;in3=1;#1000
  $display("%b        | %b        | %b   | %b   | %b   | %b   | %b   | %s            | ", address0, address1, in0, in1, in2, in3, out, "1");
  address0=1;address1=0;in0=1;in1=0;in2=0;in3=0;#1000
  $display("%b        | %b        | %b   | %b   | %b   | %b   | %b   | %s            | ", address0, address1, in0, in1, in2, in3, out, "0");
  address0=1;address1=0;in0=1;in1=0;in2=0;in3=1;#1000
  $display("%b        | %b        | %b   | %b   | %b   | %b   | %b   | %s            | ", address0, address1, in0, in1, in2, in3, out, "0");
  address0=1;address1=0;in0=1;in1=0;in2=1;in3=0;#1000
  $display("%b        | %b        | %b   | %b   | %b   | %b   | %b   | %s            | ", address0, address1, in0, in1, in2, in3, out, "0");
  address0=1;address1=0;in0=1;in1=0;in2=1;in3=1;#1000
  $display("%b        | %b        | %b   | %b   | %b   | %b   | %b   | %s            | ", address0, address1, in0, in1, in2, in3, out, "0");
  address0=1;address1=0;in0=1;in1=1;in2=0;in3=0;#1000
  $display("%b        | %b        | %b   | %b   | %b   | %b   | %b   | %s            | ", address0, address1, in0, in1, in2, in3, out, "1");
  address0=1;address1=0;in0=1;in1=1;in2=0;in3=1;#1000
  $display("%b        | %b        | %b   | %b   | %b   | %b   | %b   | %s            | ", address0, address1, in0, in1, in2, in3, out, "1");
  address0=1;address1=0;in0=1;in1=1;in2=1;in3=0;#1000
  $display("%b        | %b        | %b   | %b   | %b   | %b   | %b   | %s            | ", address0, address1, in0, in1, in2, in3, out, "1");
  address0=1;address1=0;in0=1;in1=1;in2=1;in3=1;#1000
  $display("%b        | %b        | %b   | %b   | %b   | %b   | %b   | %s            | ", address0, address1, in0, in1, in2, in3, out, "1");
  address0=1;address1=1;in0=0;in1=0;in2=0;in3=0;#1000
  $display("%b        | %b        | %b   | %b   | %b   | %b   | %b   | %s            | ", address0, address1, in0, in1, in2, in3, out, "0");
  address0=1;address1=1;in0=0;in1=0;in2=0;in3=1;#1000
  $display("%b        | %b        | %b   | %b   | %b   | %b   | %b   | %s            | ", address0, address1, in0, in1, in2, in3, out, "1");
  address0=1;address1=1;in0=0;in1=0;in2=1;in3=0;#1000
  $display("%b        | %b        | %b   | %b   | %b   | %b   | %b   | %s            | ", address0, address1, in0, in1, in2, in3, out, "0");
  address0=1;address1=1;in0=0;in1=0;in2=1;in3=1;#1000
  $display("%b        | %b        | %b   | %b   | %b   | %b   | %b   | %s            | ", address0, address1, in0, in1, in2, in3, out, "1");
  address0=1;address1=1;in0=0;in1=1;in2=0;in3=0;#1000
  $display("%b        | %b        | %b   | %b   | %b   | %b   | %b   | %s            | ", address0, address1, in0, in1, in2, in3, out, "0");
  address0=1;address1=1;in0=0;in1=1;in2=0;in3=1;#1000
  $display("%b        | %b        | %b   | %b   | %b   | %b   | %b   | %s            | ", address0, address1, in0, in1, in2, in3, out, "1");
  address0=1;address1=1;in0=0;in1=1;in2=1;in3=0;#1000
  $display("%b        | %b        | %b   | %b   | %b   | %b   | %b   | %s            | ", address0, address1, in0, in1, in2, in3, out, "0");
  address0=1;address1=1;in0=0;in1=1;in2=1;in3=1;#1000
  $display("%b        | %b        | %b   | %b   | %b   | %b   | %b   | %s            | ", address0, address1, in0, in1, in2, in3, out, "1");
  address0=1;address1=1;in0=1;in1=0;in2=0;in3=0;#1000
  $display("%b        | %b        | %b   | %b   | %b   | %b   | %b   | %s            | ", address0, address1, in0, in1, in2, in3, out, "0");
  address0=1;address1=1;in0=1;in1=0;in2=0;in3=1;#1000
  $display("%b        | %b        | %b   | %b   | %b   | %b   | %b   | %s            | ", address0, address1, in0, in1, in2, in3, out, "1");
  address0=1;address1=1;in0=1;in1=0;in2=1;in3=0;#1000
  $display("%b        | %b        | %b   | %b   | %b   | %b   | %b   | %s            | ", address0, address1, in0, in1, in2, in3, out, "0");
  address0=1;address1=1;in0=1;in1=0;in2=1;in3=1;#1000
  $display("%b        | %b        | %b   | %b   | %b   | %b   | %b   | %s            | ", address0, address1, in0, in1, in2, in3, out, "1");
  address0=1;address1=1;in0=1;in1=1;in2=0;in3=0;#1000
  $display("%b        | %b        | %b   | %b   | %b   | %b   | %b   | %s            | ", address0, address1, in0, in1, in2, in3, out, "0");
  address0=1;address1=1;in0=1;in1=1;in2=0;in3=1;#1000
  $display("%b        | %b        | %b   | %b   | %b   | %b   | %b   | %s            | ", address0, address1, in0, in1, in2, in3, out, "1");
  address0=1;address1=1;in0=1;in1=1;in2=1;in3=0;#1000
  $display("%b        | %b        | %b   | %b   | %b   | %b   | %b   | %s            | ", address0, address1, in0, in1, in2, in3, out, "0");
  address0=1;address1=1;in0=1;in1=1;in2=1;in3=1;#1000
  $display("%b        | %b        | %b   | %b   | %b   | %b   | %b   | %s            | ", address0, address1, in0, in1, in2, in3, out, "1");
  end
endmodule

mux.vcd
$date
	Thu Sep 21 21:30:20 2017
$end
$version
	Icarus Verilog
$end
$timescale
	1ps
$end
$scope module testMultiplexer $end
$var wire 1 ! out $end
$var reg 1 " address0 $end
$var reg 1 # address1 $end
$var reg 1 $ in0 $end
$var reg 1 % in1 $end
$var reg 1 & in2 $end
$var reg 1 ' in3 $end
$scope module dut $end
$var wire 1 " address0 $end
$var wire 1 # address1 $end
$var wire 1 $ in0 $end
$var wire 1 % in1 $end
$var wire 1 & in2 $end
$var wire 1 ' in3 $end
$var wire 1 ( w1 $end
$var wire 1 ) w0 $end
$var wire 1 ! out $end
$scope module m1 $end
$var wire 1 * _address $end
$var wire 1 " address $end
$var wire 1 $ in0 $end
$var wire 1 % in1 $end
$var wire 1 ) out $end
$var wire 1 + w0 $end
$var wire 1 , w1 $end
$upscope $end
$scope module m2 $end
$var wire 1 - _address $end
$var wire 1 " address $end
$var wire 1 & in0 $end
$var wire 1 ' in1 $end
$var wire 1 ( out $end
$var wire 1 . w0 $end
$var wire 1 / w1 $end
$upscope $end
$scope module m3 $end
$var wire 1 0 _address $end
$var wire 1 # address $end
$var wire 1 ) in0 $end
$var wire 1 ( in1 $end
$var wire 1 ! out $end
$var wire 1 1 w0 $end
$var wire 1 2 w1 $end
$upscope $end
$upscope $end
$upscope $end
$enddefinitions $end
#0
$dumpvars
x2
x1
x0
x/
x.
x-
x,
x+
x*
x)
x(
0'
0&
0%
0$
0#
0"
x!
$end
#50000
10
1*
1-
02
0/
0.
0,
0+
#100000
0(
0)
#150000
01
#200000
0!
#1000000
1'
#2000000
0'
1&
#2050000
1.
#2100000
1(
#3000000
1'
#4000000
0'
0&
1%
#4050000
0.
#4100000
0(
#5000000
1'
#6000000
0'
1&
#6050000
1.
#6100000
1(
#7000000
1'
#8000000
0'
0&
0%
1$
#8050000
0.
1+
#8100000
0(
1)
#8150000
11
#8200000
1!
#9000000
1'
#10000000
0'
1&
#10050000
1.
#10100000
1(
#11000000
1'
#12000000
0'
0&
1%
#12050000
0.
#12100000
0(
#13000000
1'
#14000000
0'
1&
#14050000
1.
#14100000
1(
#15000000
1'
#16000000
0'
0&
0%
0$
1#
#16050000
0.
0+
00
12
#16100000
0(
0)
01
#16150000
02
#16200000
0!
#17000000
1'
#18000000
0'
1&
#18050000
1.
#18100000
1(
#18150000
12
#18200000
1!
#19000000
1'
#20000000
0'
0&
1%
#20050000
0.
#20100000
0(
#20150000
02
#20200000
0!
#21000000
1'
#22000000
0'
1&
#22050000
1.
#22100000
1(
#22150000
12
#22200000
1!
#23000000
1'
#24000000
0'
0&
0%
1$
#24050000
0.
1+
#24100000
0(
1)
#24150000
02
#24200000
0!
#25000000
1'
#26000000
0'
1&
#26050000
1.
#26100000
1(
#26150000
12
#26200000
1!
#27000000
1'
#28000000
0'
0&
1%
#28050000
0.
#28100000
0(
#28150000
02
#28200000
0!
#29000000
1'
#30000000
0'
1&
#30050000
1.
#30100000
1(
#30150000
12
#30200000
1!
#31000000
1'
#32000000
0'
0&
0%
0$
0#
1"
#32050000
0.
0+
10
02
0*
0-
#32100000
0(
0)
11
0!
#32150000
01
1!
#32200000
0!
#33000000
1'
#33050000
1/
#33100000
1(
#34000000
0'
1&
#34050000
0/
#34100000
0(
#35000000
1'
#35050000
1/
#35100000
1(
#36000000
0'
0&
1%
#36050000
0/
1,
#36100000
0(
1)
#36150000
11
#36200000
1!
#37000000
1'
#37050000
1/
#37100000
1(
#38000000
0'
1&
#38050000
0/
#38100000
0(
#39000000
1'
#39050000
1/
#39100000
1(
#40000000
0'
0&
0%
1$
#40050000
0/
0,
#40100000
0(
0)
#40150000
01
#40200000
0!
#41000000
1'
#41050000
1/
#41100000
1(
#42000000
0'
1&
#42050000
0/
#42100000
0(
#43000000
1'
#43050000
1/
#43100000
1(
#44000000
0'
0&
1%
#44050000
0/
1,
#44100000
0(
1)
#44150000
11
#44200000
1!
#45000000
1'
#45050000
1/
#45100000
1(
#46000000
0'
1&
#46050000
0/
#46100000
0(
#47000000
1'
#47050000
1/
#47100000
1(
#48000000
0'
0&
0%
0$
1#
#48050000
0/
0,
00
12
#48100000
0(
0)
01
#48150000
02
#48200000
0!
#49000000
1'
#49050000
1/
#49100000
1(
#49150000
12
#49200000
1!
#50000000
0'
1&
#50050000
0/
#50100000
0(
#50150000
02
#50200000
0!
#51000000
1'
#51050000
1/
#51100000
1(
#51150000
12
#51200000
1!
#52000000
0'
0&
1%
#52050000
0/
1,
#52100000
0(
1)
#52150000
02
#52200000
0!
#53000000
1'
#53050000
1/
#53100000
1(
#53150000
12
#53200000
1!
#54000000
0'
1&
#54050000
0/
#54100000
0(
#54150000
02
#54200000
0!
#55000000
1'
#55050000
1/
#55100000
1(
#55150000
12
#55200000
1!
#56000000
0'
0&
0%
1$
#56050000
0/
0,
#56100000
0(
0)
#56150000
02
#56200000
0!
#57000000
1'
#57050000
1/
#57100000
1(
#57150000
12
#57200000
1!
#58000000
0'
1&
#58050000
0/
#58100000
0(
#58150000
02
#58200000
0!
#59000000
1'
#59050000
1/
#59100000
1(
#59150000
12
#59200000
1!
#60000000
0'
0&
1%
#60050000
0/
1,
#60100000
0(
1)
#60150000
02
#60200000
0!
#61000000
1'
#61050000
1/
#61100000
1(
#61150000
12
#61200000
1!
#62000000
0'
1&
#62050000
0/
#62100000
0(
#62150000
02
#62200000
0!
#63000000
1'
#63050000
1/
#63100000
1(
#63150000
12
#63200000
1!
